MANIFEST.in
README.rst
requirements-test.txt
requirements.txt
setup.cfg
setup.py
ps_tree/__init__.py
ps_tree/views.py
ps_tree.egg-info/PKG-INFO
ps_tree.egg-info/SOURCES.txt
ps_tree.egg-info/dependency_links.txt
ps_tree.egg-info/not-zip-safe
ps_tree.egg-info/pbr.json
ps_tree.egg-info/requires.txt
ps_tree.egg-info/top_level.txt
ps_tree/static/css/__ps_tree.css
ps_tree/static/css/main.css
ps_tree/static/css/vendor/jqtree.css
ps_tree/static/img/jqtree-circle.png
ps_tree/static/js/__ps_tree.js
ps_tree/static/js/jqTreeContextMenu.js
ps_tree/static/js/main.js
ps_tree/static/js/vendor/jquery.js
ps_tree/static/js/vendor/tree.jquery.js
ps_tree/templates/ps_tree/toolbar.jinja2
ps_tree/templates/ps_tree/tree.jinja2
ps_tree/tests/__init__.py
ps_tree/tests/integration_test.py
ps_tree/tests/test_common.py
ps_tree/tests/tree.py
ps_tree/tests/unit_tests.py