Metadata-Version: 1.1
Name: ps-tree
Version: 0.0.1.post0
Summary: JQuery tree structure in pyramid_sacrud or anywhere else.
Home-page: http://github.com/ITCase/ps_tree/
Author: Svintsov Dmitry
Author-email: sacrud@uralbash.ru
License: MIT
Platform: UNKNOWN
Classifier: Development Status :: 5 - Production/Stable
Classifier: Environment :: Web Environment
Classifier: Intended Audience :: Developers
Classifier: License :: OSI Approved :: MIT License
Classifier: Operating System :: OS Independent
Classifier: Programming Language :: Python
Classifier: Programming Language :: Python :: 2.6
Classifier: Programming Language :: Python :: 2.7
Classifier: Programming Language :: Python :: 3
Classifier: Programming Language :: Python :: 3.2
Classifier: Programming Language :: Python :: 3.3
Classifier: Programming Language :: Python :: 3.4
Classifier: Framework :: Pyramid 
Classifier: Topic :: Internet
Classifier: Topic :: Database
